.gitignore
.gitmodules
.travis.yml
CMakeLists.txt
LICENSE
Makefile
PYBIND_README.md
README.md
config.cfg
make_and_run_binder.py
setup.py
bdsg.egg-info/PKG-INFO
bdsg.egg-info/SOURCES.txt
bdsg.egg-info/dependency_links.txt
bdsg.egg-info/top_level.txt
bdsg/cmake_bindings/bdsg.cpp
bdsg/cmake_bindings/bdsg.modules
bdsg/cmake_bindings/bdsg.sources
bdsg/cmake_bindings/bdsg/odgi.cpp
bdsg/cmake_bindings/bdsg/internal/is_single_stranded.cpp
bdsg/cmake_bindings/bdsg/internal/packed_structs.cpp
bdsg/cmake_bindings/bdsg/internal/utility.cpp
bdsg/cmake_bindings/bdsg/internal/wang_hash.cpp
bdsg/cmake_bindings/bdsg/overlays/packed_path_position_overlay.cpp
bdsg/cmake_bindings/bdsg/overlays/packed_subgraph_overlay.cpp
bdsg/cmake_bindings/bdsg/overlays/path_position_overlays.cpp
bdsg/cmake_bindings/bdsg/overlays/vectorizable_overlays.cpp
bdsg/cmake_bindings/bdsg/overlays/vectorizable_overlays_1.cpp
bdsg/cmake_bindings/handlegraph/handle_graph.cpp
bdsg/cmake_bindings/handlegraph/mutable_path_mutable_handle_graph.cpp
bdsg/cmake_bindings/handlegraph/path_handle_graph.cpp
bdsg/cmake_bindings/handlegraph/path_position_handle_graph.cpp
bdsg/cmake_bindings/handlegraph/serializable_handle_graph.cpp
bdsg/cmake_bindings/handlegraph/types.cpp
bdsg/cmake_bindings/std/bdsg/internal/binder_hook_bind.cpp
bdsg/deps/BBHash/.travis.yml
bdsg/deps/BBHash/BooPHF.h
bdsg/deps/BBHash/LICENSE
bdsg/deps/BBHash/README.md
bdsg/deps/BBHash/bootest.cpp
bdsg/deps/BBHash/example.cpp
bdsg/deps/BBHash/example_custom_hash.cpp
bdsg/deps/BBHash/makefile
bdsg/deps/DYNAMIC/.gitignore
bdsg/deps/DYNAMIC/CMakeLists.txt
bdsg/deps/DYNAMIC/LICENSE
bdsg/deps/DYNAMIC/README.md
bdsg/deps/DYNAMIC/benchmark.cpp
bdsg/deps/DYNAMIC/cw-bwt.cpp
bdsg/deps/DYNAMIC/debug.cpp
bdsg/deps/DYNAMIC/h0_lz77.cpp
bdsg/deps/DYNAMIC/rle_bwt.cpp
bdsg/deps/DYNAMIC/rle_lz77_v1.cpp
bdsg/deps/DYNAMIC/rle_lz77_v2.cpp
bdsg/deps/DYNAMIC/wm_string.cpp
bdsg/deps/DYNAMIC/include/dynamic/dynamic.hpp
bdsg/deps/DYNAMIC/include/dynamic/algorithms/cw_bwt.hpp
bdsg/deps/DYNAMIC/include/dynamic/algorithms/h0_lz77.hpp
bdsg/deps/DYNAMIC/include/dynamic/algorithms/rle_lz77_v1.hpp
