Metadata-Version: 1.0
Name: bdsg
Version: 0.2
Summary: Library for BiDirected Sequence Graphs
Home-page: UNKNOWN
Author: vgteam
Author-email: anovak@soe.ucsc.edu
License: UNKNOWN
Platform: UNKNOWN
